README.rst
setup.cfg
setup.py
src/ez_setup.py
src/BetaLibrary/__init__.py
src/BetaLibrary/version.py
src/BetaLibrary/keywords/__init__.py
src/BetaLibrary/keywords/_android_utils.py
src/BetaLibrary/keywords/_applicationmanagement.py
src/BetaLibrary/keywords/_element.py
src/BetaLibrary/keywords/_keyevent.py
src/BetaLibrary/keywords/_logging.py
src/BetaLibrary/keywords/_runonfailure.py
src/BetaLibrary/keywords/_screenshot.py
src/BetaLibrary/keywords/_touch.py
src/BetaLibrary/keywords/_waiting.py
src/BetaLibrary/keywords/keywordgroup.py
src/BetaLibrary/locators/__init__.py
src/BetaLibrary/locators/elementfinder.py
src/BetaLibrary/utils/__init__.py
src/BetaLibrary/utils/applicationcache.py
src/netease_appiumlibrary.egg-info/PKG-INFO
src/netease_appiumlibrary.egg-info/SOURCES.txt
src/netease_appiumlibrary.egg-info/dependency_links.txt
src/netease_appiumlibrary.egg-info/requires.txt
src/netease_appiumlibrary.egg-info/top_level.txt