Metadata-Version: 1.1
Name: netease-appiumlibrary
Version: 1.3.5
Summary: app testing library for Robot Framework
Home-page: https://github.com/jollychang/robotframework-appiumlibrary
Author: William Zhang, Xie Lieping, Jari Nurminen, Serhat Bolsu
Author-email: <jollychang@gmail.com>, <frankbp@gmail.com>
License: Apache License 2.0
Keywords: robotframework testing testautomation mobile appium webdriver app
Platform: any
Classifier: Development Status :: 5 - Production/Stable
Classifier: License :: OSI Approved :: Apache Software License
Classifier: Operating System :: OS Independent
Classifier: Programming Language :: Python
Classifier: Topic :: Software Development :: Testing
